pyloid_server_adapter/__Init__.py
pyloid_server_adapter/base_adapter.py
pyloid_server_adapter/context.py
pyloid_server_adapter/fastapi_adapter.py
pyloid_server_adapter/utils.py
pyloid_server_adapter-0.2.2.dist-info/METADATA
pyloid_server_adapter-0.2.2.dist-info/WHEEL
pyloid_server_adapter-0.2.2.dist-info/RECORD
