Metadata-Version: 2.4
Name: pyloid-server-adapter
Version: 0.2.2
Summary: PyLoid Server Adapter
Author-email: hyeonho cho <111675679+aesthetics-of-record@users.noreply.github.com>
Requires-Python: >=3.9
Provides-Extra: fastapi
Requires-Dist: fastapi; extra == 'fastapi'
Requires-Dist: pydantic; extra == 'fastapi'
Provides-Extra: flask
Requires-Dist: flask; extra == 'flask'
Requires-Dist: flask-cors; extra == 'flask'
